xlbridge/__init__.py
xlbridge/object_converter.py
xlbridge/proto_converter.py
xlbridge/reference_store.py
xlbridge/service_pb2.py
xlbridge/service_pb2_grpc.py
xlbridge/xlbridge.py
xlbridge/xlbridge_servicer.py
xlbridge-0.4.0b0.dist-info/LICENSE.txt
xlbridge-0.4.0b0.dist-info/METADATA
xlbridge-0.4.0b0.dist-info/WHEEL
xlbridge-0.4.0b0.dist-info/top_level.txt
xlbridge-0.4.0b0.dist-info/RECORD
