Metadata-Version: 2.1
Name: xlbridge
Version: 0.4.0b0
Summary: Create Excel user-defined formulas (UDFs) using Python
Home-page: https://xlbridge.qaplix.se
Author: Michael Hemph
Author-email: michael.hemph@gmail.com
License: Proprietary
Project-URL: Bug Tracker, https://github.com/qaplix/xlbridge/issues
Platform: UNKNOWN
Classifier: Programming Language :: Python :: 3
Classifier: Development Status :: 4 - Beta
Classifier: Operating System :: OS Independent
Classifier: Intended Audience :: Developers
Classifier: Intended Audience :: Science/Research
Classifier: Intended Audience :: Financial and Insurance Industry
Classifier: License :: Other/Proprietary License
Classifier: Topic :: Office/Business :: Financial :: Spreadsheet
Requires-Python: >=3.6
License-File: LICENSE.txt
Requires-Dist: grpcio
Requires-Dist: protobuf
